ultrametric_matrix_tools-0.1.1.dist-info/METADATA
ultrametric_matrix_tools-0.1.1.dist-info/WHEEL
ultrametric_matrix_tools/__init__.py
ultrametric_matrix_tools/ultrametric_matrix_tools.abi3.so
ultrametric_matrix_tools-0.1.1.dist-info/RECORD
