Metadata-Version: 2.1
Name: ultrametric-matrix-tools
Version: 0.1.1
Summary: Toolbox that provides functions and data structures to generate and handle ultrametric matrices.
Keywords: math,linear,algebra,ultrametric tree,ultrametric matrix
Author: Andy Oertel
Author-email: andy.oertel@cs.lth.se
Maintainer-email: Andy Oertel <andy.oertel@cs.lth.se>
License:                                  Apache License
Requires-Python: >=3.6
